{
	"name": "brickbattle-remix-global",
        "emitLegacyScripts": false,
	"tree": {
		"$className": "DataModel",
		"ReplicatedStorage": {
                        "global_client": {
				"$path": "global/client/"
                        },
                        "global_shared": {
				"$path": "global/shared/"
                        },
			"development": {
				"$path": "development"
			}
        	},
        	"ServerScriptService": {
                        "global_server": {
				"$path": "global/server/"
                        }
        	}
	}
}
